bics_nornir/.gitignore
bics_nornir/__init__.py
bics_nornir/plugins/__init__.py
bics_nornir/plugins/connections/__init__.py
bics_nornir/plugins/connections/ncclient.py
bics_nornir/plugins/tasks/__init__.py
bics_nornir/plugins/tasks/data/__init__.py
bics_nornir/plugins/tasks/data/download_configs.py
bics_nornir/plugins/tasks/data/load_merge_yaml.py
bics_nornir/plugins/tasks/data/load_service_intents.py
bics_nornir/plugins/tasks/data/render_templates.py
bics_nornir/plugins/tasks/networking/__init__.py
bics_nornir/plugins/tasks/networking/nc.py
bics_nornir/plugins/tasks/services/__init__.py
bics_nornir/plugins/tasks/services/eline.py
bics_nornir-0.1.0.dist-info/WHEEL
bics_nornir-0.1.0.dist-info/METADATA
bics_nornir-0.1.0.dist-info/RECORD
