Metadata-Version: 2.1
Name: bics-nornir
Version: 0.1.0
Summary: Specific plugins for Nornir2
Home-page: https://github.com/wdesmedt/bics_nornir
License: Apache-2.0
Author: Walter De Smedt
Author-email: walter.de.smedt@gmail.com
Requires-Python: >=3.6,<4.0
Classifier: Development Status :: 3 - Alpha
Classifier: License :: OSI Approved :: Apache Software License
Classifier: Programming Language :: Python :: 3
Classifier: Programming Language :: Python :: 3.6
Classifier: Programming Language :: Python :: 3.7
Requires-Dist: jinja2 (>=2,<3)
Requires-Dist: ncclient (>=0.6.3,<0.7.0)
Requires-Dist: nornir (>=2.1,<3.0)
Requires-Dist: pydantic (>=0.18.2,<0.19.0)
Requires-Dist: ruamel.yaml (>=0.15.85,<0.16.0)
Requires-Dist: xmltodict (>=0.12.0,<0.13.0)
Project-URL: Repository, https://github.com/wdesmedt/bics_nornir
